quantclean.py
quantclean-0.0.2.dist-info/METADATA
quantclean-0.0.2.dist-info/WHEEL
quantclean-0.0.2.dist-info/top_level.txt
quantclean-0.0.2.dist-info/RECORD
