Metadata-Version: 2.1
Name: quantclean
Version: 0.0.2
Summary: Quantclean is a program that reformats every financial dataset to US Equity TradeBar
Home-page: https://github.com/ssantoshp/quantclean
Author: Santosh Passoubady
Author-email: santoshpassoubady@gmail.com
License: MIT
Platform: UNKNOWN
Requires-Dist: pandas-datareader
Requires-Dist: pandas
